cjktools/__init__.py
cjktools/__version__.py
cjktools/alternations.py
cjktools/common.py
cjktools/errors.py
cjktools/kana_table.py
cjktools/maps.py
cjktools/scripts.py
cjktools/smart_cache.py
cjktools/resources/__init__.py
cjktools/resources/auto_format.py
cjktools/resources/bilingual_dict.py
cjktools/resources/cjkdata.py
cjktools/resources/dict_format.py
cjktools/resources/kanji_list.py
cjktools/resources/kanjidic.py
cjktools/resources/languages.py
cjktools/resources/pinyin_table.py
cjktools/resources/place.py
cjktools/resources/radkdict.py
cjktools/resources/split_by_codes.py
cjktools/resources/tree.py
cjktools/resources/zhuyin_table.py
cjktools-1.7.0.dist-info/DESCRIPTION.rst
cjktools-1.7.0.dist-info/METADATA
cjktools-1.7.0.dist-info/RECORD
cjktools-1.7.0.dist-info/WHEEL
cjktools-1.7.0.dist-info/metadata.json
cjktools-1.7.0.dist-info/top_level.txt
