Metadata-Version: 2.0
Name: cjktools
Version: 1.7.0
Summary: A library for basic CJK processing and lexicography.
Home-page: http://bitbucket.org/larsyencken/cjktools/
Author: Lars Yencken
Author-email: lars@yencken.org
License: BSD
Platform: UNKNOWN
Classifier: License :: OSI Approved :: BSD License
Classifier: Programming Language :: Python
Classifier: Programming Language :: Python :: 2
Classifier: Programming Language :: Python :: 2.7
Classifier: Programming Language :: Python :: 3
Classifier: Programming Language :: Python :: 3.4
Classifier: Programming Language :: Python :: 3.5
Requires-Dist: six
